{
  "id": 5978,
  "slug": "raiz-rewards-planning-for-your-2023-travel",
  "link": "https://raiz.com.my/blog/raiz-rewards-planning-for-your-2023-travel/",
  "title": "Raiz Rewards: Planning for your 2023 travel?",
  "author": 1,
  "featured_media": 0,
  "img": "https://raiz.com.my/blog/wp-content/uploads/2022/10/Copy-of-RR-H01-900-×-506-px-3-320x180.png",
  "description": "Klik sini untuk Bahasa Melayu 17/02/2023   Raiz Rewards: Planning for your 2023 travel?   Plan for your 2023 travels with our brand partners! Flight tickets, accommodations, experiences – we’ve got all covered for you. Check out our top travel partners below and their amazing deals (just in time for the school holidays!). The best part? […]",
  "publishDate": "2023-02-17T03:54:16+00:00",
  "body": "![](https://raiz.com.my/blog/wp-content/uploads/2022/10/Copy-of-RR-H01-900-×-506-px-3.png)\n\n__[Klik sini untuk Bahasa Melayu](https://raiz.com.my/blog/raiz-rewards-merancang-percutian-2023/)__\n\n__17/02/2023__\n\n__Raiz Rewards: Planning for your 2023 travel?__\n\nPlan for your 2023 travels with our brand partners! Flight tickets, accommodations, experiences – we’ve got all covered for you. Check out our top travel partners below and their amazing deals (just in time for the school holidays!). The best part? Get cash bonus (or cashback) when you book online using “[__Raiz Rewards__](http://app.adjust.com/jsr?url=https%3A%2F%2Fye77.adj.st%2Fraiz_rewards%3Fadj_t%3D5tn8ue3_g8sxcfy%26adj_deep_link%3Draiz-my%253A%252F%252Fraiz_rewards%26adj_fallback%3Dhttps%253A%252F%252Fapp.raiz.com.my%252Frewards%26adj_deeplink_js%3D1)”! Your cashback will get invested into your Raiz account automatically.\n\nJust go to “[__Raiz Rewards__](http://app.adjust.com/jsr?url=https%3A%2F%2Fye77.adj.st%2Fraiz_rewards%3Fadj_t%3D5tn8ue3_g8sxcfy%26adj_deep_link%3Draiz-my%253A%252F%252Fraiz_rewards%26adj_fallback%3Dhttps%253A%252F%252Fapp.raiz.com.my%252Frewards%26adj_deeplink_js%3D1)” in your app, search for your favourite brand, and click the “[__Book Online Here__](http://app.adjust.com/jsr?url=https%3A%2F%2Fye77.adj.st%2Fraiz_rewards%3Fadj_t%3D5tn8ue3_g8sxcfy%26adj_deep_link%3Draiz-my%253A%252F%252Fraiz_rewards%26adj_fallback%3Dhttps%253A%252F%252Fapp.raiz.com.my%252Frewards%26adj_deeplink_js%3D1)” button. We’ll direct you to the brand’s app or website. Book like normal, and you will be on your way to get your cashback\\*.\n\nSo, as you book, you invest!\n\n*\\*Terms & Conditions apply.*\n\n__Trip.com__\n\n![](https://raiz.com.my/blog/wp-content/uploads/2023/02/Trip.com_.png)\n\n__(+up to 2.45% invested)__\n\n*   Choose from over 1.2 million hotels in more than 200 countries and book flights to over 5,000 destinations worldwide with __Trip.com__!\n\n__Airpaz__\n\n__![](https://raiz.com.my/blog/wp-content/uploads/2023/02/Airpaz.png)__\n\n__(+ 0.69% invested)__\n\n*   __Airpaz__ provides flexible payment in local currency, local languages, effortless manage booking feature, easy booking steps, best fare calendar, and 24/7 customer support.\n*   Get exclusive promotions for flights and hotels. __How?__ Just go to Raiz Rewards, choose Airpaz & tap at Book Online Here. On Airpaz’s home page, click Promo and browse for their amazing deals.\n\n__AirAsia Flight__\n\n__![](https://raiz.com.my/blog/wp-content/uploads/2023/02/AirAsia.png)__\n\n__(+3.43% invested)__\n\n__Special Deal: 5 million free seats!__\n\n*   AirAsia launched its first free seats for the year with __5 million FREE\\* seats__ up for grabs.\n*   __Booking period: __Now – 19 February 2023\n*   __Travel period:__ 1 March – 10 December 2023  \n    *\\*Terms & conditions apply.*\n\n__Klook__\n\n![](https://raiz.com.my/blog/wp-content/uploads/2023/02/Klook.png)\n\n__(+ up to 3.5% invested)__\n\n__Special Deals: School holiday is more fun with Klook!__\n\n*   Get __up to RM50 off__ for all family fun activities (with minimum spend of RM500)\n*   Get __up to 50% off__ for popular Malaysia attractions!\n\n__Agoda__\n\n![](https://raiz.com.my/blog/wp-content/uploads/2023/02/Agoda.png)\n\n__(+2.94% invested)__\n\n__Special Deals:__\n\n*   Get __up to 30% off__ for international hotel rates.\n*   View other deals and coupons for more savings. __How?__ Just go to Raiz Rewards, choose to Agoda & tap at Book Online Here. On Agoda’s home page, click Coupons & Deals.\n\n[![raiz rewards](https://raiz.com.my/blog/wp-content/uploads/2021/11/Explore-Raiz-Rewards.gif)](https://ye77.adj.st/raiz_rewards?adj_t=lwt55og_doqwx9i&adj_deep_link=raiz-my%3A%2F[%E2%80%A6]iz_rewards&adj_fallback=https%3A%2F%2Fapp.raiz.com.my%2Frewards)\n\nraiz rewards\n\n__Need more details?__\n\nRead the FAQ on Raiz Rewards [__here__](https://raiz.com.my/my-support/)\n\n---\n\nGet RM10 bonuWant to use Raiz Rewards but don’t have the Raiz App?\n\nDownload it for free in the App store or the Webapp [__here.__](https://app.adjust.com/4vnqz2h_q39miv7?fallback=https%3A%2F%2Fapp.raiz.com.my%2Fregistration)\n\n---\n\n__*Important Information*__\n\n*The information on this website is general advice only. This means it does not consider any person’s investment objectives, financial situation, or investment needs. If you are an investor, you should consult your licensed adviser before acting on any information contained in this article to fully understand the benefits and risks associated with the Raiz product.*\n\n*The information on this website is confidential. It must not be reproduced, distributed, or disclosed to any other person. The information is based on assumptions or market conditions that change without notice. This will impact the accuracy of the information.*\n\n*Under no circumstances is the information to be used by, or presented to, a person for the purposes of deciding about investing in Raiz.*",
  "category": 2,
  "bodyImages": [
    {
      "link": "https://raiz.com.my/blog/wp-content/uploads/2022/10/Copy-of-RR-H01-900-×-506-px-3.png",
      "description": "",
      "title": "",
      "postId": 5978
    },
    {
      "link": "https://raiz.com.my/blog/wp-content/uploads/2023/02/Trip.com_.png",
      "description": "",
      "title": "",
      "postId": 5978
    },
    {
      "link": "https://raiz.com.my/blog/wp-content/uploads/2023/02/Airpaz.png",
      "description": "",
      "title": "",
      "postId": 5978
    },
    {
      "link": "https://raiz.com.my/blog/wp-content/uploads/2023/02/AirAsia.png",
      "description": "",
      "title": "",
      "postId": 5978
    },
    {
      "link": "https://raiz.com.my/blog/wp-content/uploads/2023/02/Klook.png",
      "description": "",
      "title": "",
      "postId": 5978
    },
    {
      "link": "https://raiz.com.my/blog/wp-content/uploads/2023/02/Agoda.png",
      "description": "",
      "title": "",
      "postId": 5978
    },
    {
      "link": "https://raiz.com.my/blog/wp-content/uploads/2021/11/Explore-Raiz-Rewards.gif",
      "description": "raiz rewards",
      "title": "raiz rewards",
      "postId": 5978
    }
  ]
}
